configs/__init__.py
configs/bad_images selected by gemini.txt
configs/config.yaml
configs/data_config.yaml
configs/duplicates selected by gemini.txt
configs/misclassified selected by gemini.txt
configs/sweep.yaml
rocks_classifier/__init__.py
rocks_classifier/_modidx.py
rocks_classifier/bot.py
rocks_classifier/callbacks/__init__.py
rocks_classifier/callbacks/callbacks.py
rocks_classifier/configs/__init__.py
rocks_classifier/configs/bad_images selected by gemini.txt
rocks_classifier/configs/config.yaml
rocks_classifier/configs/data_config.yaml
rocks_classifier/configs/duplicates selected by gemini.txt
rocks_classifier/configs/misclassified selected by gemini.txt
rocks_classifier/configs/sweep.yaml
rocks_classifier/data/__init__.py
rocks_classifier/data/download.py
rocks_classifier/data/preprocess.py
rocks_classifier/data/utils.py
rocks_classifier/models/__init__.py
rocks_classifier/models/models.py
rocks_classifier/models/predict.py
rocks_classifier/models/train.py
rocks_classifier/models/utils.py
rocks_classifier/visualization/__init__.py
rocks_classifier/visualization/plot.py
rocks_classifier-0.1.2.dist-info/LICENSE
rocks_classifier-0.1.2.dist-info/METADATA
rocks_classifier-0.1.2.dist-info/WHEEL
rocks_classifier-0.1.2.dist-info/entry_points.txt
rocks_classifier-0.1.2.dist-info/top_level.txt
rocks_classifier-0.1.2.dist-info/RECORD
