Metadata-Version: 2.1
Name: rocks-classifier
Version: 0.1.2
Summary: Rock classifier deployed on railway and monitored using Weights and Biases!
Home-page: https://github.com/udaylunawat/Whats-this-rock
Author: udaylunawat
Author-email: udaylunawat@gmail.com
License: Apache Software License 2.0
Keywords: nbdev jupyter notebook python
Classifier: Development Status :: 4 - Beta
Classifier: Intended Audience :: Developers
Classifier: Natural Language :: English
Classifier: Programming Language :: Python :: 3.7
Classifier: Programming Language :: Python :: 3.8
Classifier: Programming Language :: Python :: 3.9
Classifier: Programming Language :: Python :: 3.10
Classifier: License :: OSI Approved :: Apache Software License
Requires-Python: >=3.7
License-File: LICENSE
Requires-Dist: numpy
Requires-Dist: wandb
Requires-Dist: pandas
Requires-Dist: hydra-core
Requires-Dist: scikit-learn
Requires-Dist: tensorflow-addons
Requires-Dist: opencv-python-headless
Requires-Dist: split-folders
Requires-Dist: keras-cv
Requires-Dist: tensorflow-datasets
Requires-Dist: opencv-python
Requires-Dist: pillow
Requires-Dist: matplotlib
Requires-Dist: seaborn
Requires-Dist: plotly
Requires-Dist: nbdev
Requires-Dist: pre-commit
Requires-Dist: fastai
Requires-Dist: tensorflow
Requires-Dist: python-telegram-bot
Provides-Extra: cpu
Requires-Dist: tensorflow ; extra == 'cpu'
Provides-Extra: dev
Requires-Dist: opencv-python ; extra == 'dev'
Requires-Dist: pillow ; extra == 'dev'
Requires-Dist: matplotlib ; extra == 'dev'
Requires-Dist: seaborn ; extra == 'dev'
Requires-Dist: plotly ; extra == 'dev'
Requires-Dist: nbdev ; extra == 'dev'
Requires-Dist: pre-commit ; extra == 'dev'
Requires-Dist: fastai ; extra == 'dev'
Requires-Dist: tensorflow ; extra == 'dev'
Provides-Extra: gpu
Requires-Dist: tensorflow-gpu ; extra == 'gpu'
